tangram_globe/GlobeToggle.vue
tangram_globe/__init__.py
tangram_globe/index.ts
tangram_globe/dist-frontend/index.css
tangram_globe/dist-frontend/index.js
tangram_globe/dist-frontend/index.js.map
tangram_globe/dist-frontend/plugin.json
tangram_globe/package.json
tangram_globe-0.3.0.dist-info/METADATA
tangram_globe-0.3.0.dist-info/WHEEL
tangram_globe-0.3.0.dist-info/entry_points.txt
tangram_globe-0.3.0.dist-info/RECORD
